dvadmin_third/__init__.py
dvadmin_third/admin.py
dvadmin_third/apps.py
dvadmin_third/dingtalk_auth.py
dvadmin_third/feishu_auth.py
dvadmin_third/models.py
dvadmin_third/settings.py
dvadmin_third/urls.py
dvadmin_third/fixtures/__init__.py
dvadmin_third/fixtures/init_dictionary.json
dvadmin_third/fixtures/init_menu.json
dvadmin_third/fixtures/init_systemconfig.json
dvadmin_third/fixtures/initialize.py
dvadmin_third/migrations/0001_initial.py
dvadmin_third/migrations/0002_initial.py
dvadmin_third/migrations/__init__.py
dvadmin_third/templates/h5/index.html
dvadmin_third/templates/h5/static/fail.png
dvadmin_third/templates/h5/static/index.63b34199.css
dvadmin_third/templates/h5/static/logo.png
dvadmin_third/templates/h5/static/success.png
dvadmin_third/templates/h5/static/uni.webview.js
dvadmin_third/templates/h5/static/fonts/uniicons.b6d3756e.ttf
dvadmin_third/templates/h5/static/img/fail.47f4b282.png
dvadmin_third/templates/h5/static/img/success.d46f6e83.png
dvadmin_third/templates/h5/static/js/chunk-vendors.091ebf81.js
dvadmin_third/templates/h5/static/js/index.8e2320d5.js
dvadmin_third/templates/h5/static/js/pages-clause-privacy.e3f67a28.js
dvadmin_third/templates/h5/static/js/pages-clause-termsService.2e0192b5.js
dvadmin_third/templates/h5/static/js/pages-index-index.661aab74.js
dvadmin_third/templates/h5/static/js/pages-index-index~pages-login-index~pages-scanLogin-index.47a9c521.js
dvadmin_third/templates/h5/static/js/pages-index-index~pages-scanLogin-index.31c9b02a.js
dvadmin_third/templates/h5/static/js/pages-login-index.c60be414.js
dvadmin_third/templates/h5/static/js/pages-loginstatus-fail.3be80d70.js
dvadmin_third/templates/h5/static/js/pages-loginstatus-invalid.af2124a1.js
dvadmin_third/templates/h5/static/js/pages-loginstatus-pastdue.efda9a27.js
dvadmin_third/templates/h5/static/js/pages-loginstatus-scanned.47bba57b.js
dvadmin_third/templates/h5/static/js/pages-loginstatus-success.55cf9182.js
dvadmin_third-5.0.0.dist-info/METADATA
dvadmin_third-5.0.0.dist-info/WHEEL
dvadmin_third-5.0.0.dist-info/top_level.txt
dvadmin_third-5.0.0.dist-info/RECORD
