Metadata-Version: 2.1
Name: dvadmin-third
Version: 5.0.0
Summary: dvadmin-third 插件是dvadmin的一个第三方用户管理插件，支持微信、企业微信、钉钉、飞书、H5页面扫码登录，支持扩展微信、企业微信、钉钉、飞书等用户信息类，以及SSO单点登录等功能(部分功能开发中)。
Home-page: https://gitee.com/huge-dream/dvadmin-third
Author: 李强
Author-email: 1206709430@qq.com
Classifier: Programming Language :: Python :: 3
Classifier: License :: OSI Approved :: MIT License
Classifier: Operating System :: OS Independent
Requires-Python: >=3.6, <4
Requires-Dist: netifaces (>=0.11.0)
Requires-Dist: django-redis (>=5.0.0)
